{
    "name": "The Avengers",
    "shortDesc": "Die Avengers müssen zusammenarbeiten, um die Erde vor Loki und seiner Armee von Außerirdischen zu schützen, die die Welt erobern wollen.",
    "cover": "https://www.movieposters.com/cdn/shop/products/avengers.intl.125809.ar_480x.progressive.jpg",
    "description": "Loki, der Bruder von Thor, kehrt zurück, um die Erde zu erobern. Nick Fury stellt ein Team von Superhelden zusammen – Iron Man, Captain America, Thor, Hulk, Black Widow und Hawkeye –, um gegen die Bedrohung zu kämpfen und die Welt zu retten.",
    "playtime": "02:23:00",
    "releaseDate": "2012-05-04",
    "broadcastingTimes": "[\"15:30\", \"19:00\", \"22:15\"]",
    "topCast": "[\"Robert Downey Jr.\", \"Chris Evans\", \"Mark Ruffalo\", \"Chris Hemsworth\", \"Scarlett Johansson\", \"Tom Hiddleston\"]",
    "trailerUrl": "https://www.youtube.com/watch?v=eOrNdBpGMv8",
    "director": "Joss Whedon",
    "genre": "[\"Action\", \"Abenteuer\", \"Sci-Fi\"]",
    "rating": 4.6,
    "price": 11.99,
    "hallId": 2
  }
  